Metadata-Version: 2.2
Name: libs411
Version: 0.0.4
Summary: a project for development
Author: your name
Author-email: fulei <fulei@411.com>
Dynamic: author
